gravpop/__init__.py
gravpop/hyper/__init__.py
gravpop/hyper/expectation.py
gravpop/hyper/hybrid.py
gravpop/hyper/selection.py
gravpop/hyper/standard.py
gravpop/models/__init__.py
gravpop/models/generic/__init__.py
gravpop/models/generic/abstract.py
gravpop/models/generic/analytic_to_sampled.py
gravpop/models/generic/gaussian.py
gravpop/models/generic/truncatedgaussian1D.py
gravpop/models/generic/truncatedgaussian2D.py
gravpop/models/generic/uniform.py
gravpop/models/mass/__init__.py
gravpop/models/mass/mass.py
gravpop/models/redshift/__init__.py
gravpop/models/redshift/redshift.py
gravpop/models/sample/__init__.py
gravpop/models/sample/truncnorm_sample.py
gravpop/models/spin/__init__.py
gravpop/models/spin/analytic_models.py
gravpop/models/spin/iid_defaults.py
gravpop/models/spin/seperated_models.py
gravpop/models/spin/truncated_gaussian.py
gravpop/models/utils/__init__.py
gravpop/models/utils/utils.py
gravpop/models/utils/mvnorm2d/__init__.py
gravpop/models/utils/mvnorm2d/mvnorm2d.py
gravpop/plots/__init__.py
gravpop/plots/grid.py
gravpop/plots/mass.py
gravpop/plots/redshift.py
gravpop/plots/spin_magnitude.py
gravpop/plots/spin_orientation.py
gravpop/post_processing/__init__.py
gravpop/post_processing/posterior.py
gravpop/sampler/__init__.py
gravpop/sampler/constraints.py
gravpop/sampler/custompriors.py
gravpop/sampler/sampler.py
gravpop/test_utils/__init__.py
gravpop/test_utils/gwpop_mimic.py
gravpop/utils/__init__.py
gravpop/utils/beta_parameter_conversion.py
gravpop/utils/reading_data.py
gravpop/utils/vmap.py
test/__init__.py
test/conftest.py
test/test_2D_gaussian.py
test/test_gwpop_mimic.py
test/test_likelihood.py
test/test_models.py
test/test_sampler.py
test/test_spin_models.py
test/testing_utils.py
gravpop-0.1.1.dist-info/METADATA
gravpop-0.1.1.dist-info/WHEEL
gravpop-0.1.1.dist-info/top_level.txt
gravpop-0.1.1.dist-info/RECORD
