Metadata-Version: 2.1
Name: gravpop
Version: 0.1.1
Summary: Package to perform astrophysical population modelling using gravitational waves, 
Home-page: https://github.com/potatoasad/gravpop
Author: Asad Hussain
Author-email: asadh@utexas.edu
